{"global_step": 249240, "episode/reward": -598.0546214033271, "episode/length": 1720, "episode/laps": 0, "episode/crashes": 1, "episode/on_track_pct": 42.848837209302324, "episode/number": 92, "curriculum/level": 0, "curriculum/track_level": 1, "curriculum/track_name": "Wide Oval", "curriculum/tier": "A-easy", "curriculum/rolling_mean": -961.7326780426483, "curriculum/threshold": 30.0, "curriculum/is_replay": 0, "_timestamp": 1775341398.7577655, "_runtime": 2349.1662056446075, "_step": 249240, "ppo/policy_loss": NaN, "ppo/value_loss": NaN, "ppo/entropy": NaN, "ppo/approx_kl": NaN, "ppo/clip_fraction": NaN, "ppo/explained_variance": -0.001440882682800293, "ppo/learning_rate": 0.00028669619199999996, "ppo/entropy_coef": 0.0095871232, "ppo/grad_norm": NaN, "ppo/update": 15, "ppo/early_stopped": 1, "system/steps_per_sec": 106.5087593112604, "system/elapsed_hours": 0.6409491268131468}